CHANGELOG.md
LICENSE
MANIFEST.in
README.md
setup.cfg
setup.py
pip_services3_data/IFilteredPageReader.py
pip_services3_data/IFilteredReader.py
pip_services3_data/IGetter.py
pip_services3_data/ILoader.py
pip_services3_data/IPartialUpdater.py
pip_services3_data/IQuerablePageReader.py
pip_services3_data/IQuerableReader.py
pip_services3_data/ISaver.py
pip_services3_data/ISetter.py
pip_services3_data/IWriter.py
pip_services3_data/__init__.py
pip_services3_data.egg-info/PKG-INFO
pip_services3_data.egg-info/SOURCES.txt
pip_services3_data.egg-info/dependency_links.txt
pip_services3_data.egg-info/requires.txt
pip_services3_data.egg-info/top_level.txt
pip_services3_data.egg-info/zip-safe
pip_services3_data/persistence/FilePersistence.py
pip_services3_data/persistence/IdentifiableFilePersistence.py
pip_services3_data/persistence/IdentifiableMemoryPersistence.py
pip_services3_data/persistence/JsonFilePersister.py
pip_services3_data/persistence/MemoryPersistence.py
pip_services3_data/persistence/__init__.py
test/persistence/DummyFilePersistence.py
test/persistence/DummyMemoryPersistence.py
test/persistence/__init__.py
test/persistence/test_DummyFilePersistence.py
test/persistence/test_DummyMemoryPersistence.py
test/persistence/test_JsonFilePersister.py